LICENSE
MANIFEST.in
README.md
requirements.txt
setup.cfg
setup.py
midtermgeos/__init__.py
midtermgeos/midtermgeos.py
midtermgeos.egg-info/PKG-INFO
midtermgeos.egg-info/SOURCES.txt
midtermgeos.egg-info/dependency_links.txt
midtermgeos.egg-info/not-zip-safe
midtermgeos.egg-info/top_level.txt