Metadata-Version: 2.1
Name: midtermgeos
Version: 0.0.1
Summary: for geog midterm
Home-page: https://github.com/Feng96/midtermgeos
Author: Yinan Feng
Author-email: feng.945@osu.edu
License: MIT license
Keywords: midtermgeos
Classifier: Development Status :: 2 - Pre-Alpha
Classifier: Intended Audience :: Developers
Classifier: License :: OSI Approved :: MIT License
Classifier: Natural Language :: English
Classifier: Programming Language :: Python :: 3
Classifier: Programming Language :: Python :: 3.7
Classifier: Programming Language :: Python :: 3.8
Classifier: Programming Language :: Python :: 3.9
Classifier: Programming Language :: Python :: 3.10
Requires-Python: >=3.7
License-File: LICENSE
